HardwareID/__init__.py
HardwareID/core.py
hardwareid-1.0.0.dist-info/licenses/LICENSE
hardwareid-1.0.0.dist-info/METADATA
hardwareid-1.0.0.dist-info/WHEEL
hardwareid-1.0.0.dist-info/top_level.txt
hardwareid-1.0.0.dist-info/RECORD
