Metadata-Version: 2.4
Name: hardwareid
Version: 1.0.0
Summary: Cross-platform hardware identification library
Author-email: Konstantin Gorshkov <kostya_gorshkov_06@vk.com>
License: Copyright © 2025 Konstantin Gorshkov
Project-URL: Homepage, https://github.com/kostya2023/hardwareid
Keywords: hwid,hardware,fingerprint,cross-platform
Classifier: License :: OSI Approved :: MIT License
Classifier: Operating System :: Microsoft :: Windows
Classifier: Operating System :: POSIX :: Linux
Classifier: Programming Language :: Python :: 3
Classifier: Topic :: Security
Classifier: Topic :: System :: Hardware
License-File: LICENSE
Requires-Dist: pywin32>=300; sys_platform == "win32"
Requires-Dist: WMI==1.5.1; sys_platform == "win32"
Dynamic: license-file
